[
  {
    "className": "Pre-School Class",
    "lesson": "13 Lessons",
    "students": "20 Students",
    "location": "Alice Bohm , Linda Glendell",
    "price": 90,
    "Thumb": "https://i.ibb.co/bRkd8K9/work1-57b5bee5.jpg"
  },
  {
    "className": "Pre-School Class",
    "lesson": "13 Lessons",
    "students": "20 Students",
    "location": "Alice Bohm , Linda Glendell",
    "price": 90,
    "Thumb": "https://i.ibb.co/qYHTqhc/work6-1c396ff1.jpg"
  },
  {
    "className": "Pre-School Class",
    "lesson": "13 Lessons",
    "students": "20 Students",
    "location": "Alice Bohm , Linda Glendell",
    "price": 90,
    "Thumb": "https://i.ibb.co/bRkd8K9/work1-57b5bee5.jpg"
  },
  {
    "className": "Pre-School Class",
    "lesson": "13 Lessons",
    "students": "20 Students",
    "location": "Alice Bohm , Linda Glendell",
    "price": 90,
    "Thumb": "https://i.ibb.co/G3zs9DZ/work5-e0be6d32.jpg"
  },
  {
    "className": "Pre-School Class",
    "lesson": "13 Lessons",
    "students": "20 Students",
    "location": "Alice Bohm , Linda Glendell",
    "price": 90,
    "Thumb": "https://i.ibb.co/rtYxGQN/work4-9cdc70c5.jpg"
  },
  {
    "className": "Pre-School Class",
    "lesson": "13 Lessons",
    "students": "20 Students",
    "location": "Alice Bohm , Linda Glendell",
    "price": 90,
    "Thumb": "https://i.ibb.co/Rp13mnD/work2-cf6a672a.jpg"
  },
  {
    "className": "Pre-School Class",
    "lesson": "13 Lessons",
    "students": "20 Students",
    "location": "Alice Bohm , Linda Glendell",
    "price": 90,
    "Thumb": "https://i.ibb.co/pZzxx7K/blog3-6f3bec1f.jpg"
  },
  {
    "className": "Pre-School Class",
    "lesson": "13 Lessons",
    "students": "20 Students",
    "location": "Alice Bohm , Linda Glendell",
    "price": 90,
    "Thumb": "https://i.ibb.co/kqPXDM5/blog2-8a1e528f.jpg"
  },
  {
    "className": "Pre-School Class",
    "lesson": "13 Lessons",
    "students": "20 Students",
    "location": "Alice Bohm , Linda Glendell",
    "price": 90,
    "Thumb": "https://i.ibb.co/9nxBkWs/blog-0419b18d.jpg"
  }
]
